watchman/__init__.py
watchman/checks.py
watchman/constants.py
watchman/decorators.py
watchman/models.py
watchman/settings.py
watchman/urls.py
watchman/utils.py
watchman/views.py
watchman/management/__init__.py
watchman/management/commands/__init__.py
watchman/management/commands/watchman.py
watchman/templates/watchman/base.html
watchman/templates/watchman/dashboard.html
django_watchman-1.3.0.dist-info/AUTHORS.rst
django_watchman-1.3.0.dist-info/LICENSE
django_watchman-1.3.0.dist-info/METADATA
django_watchman-1.3.0.dist-info/WHEEL
django_watchman-1.3.0.dist-info/top_level.txt
django_watchman-1.3.0.dist-info/RECORD
