Metadata-Version: 1.1
Name: django-watchman
Version: 1.3.0
Summary: django-watchman exposes a status endpoint for your backing services
Home-page: https://github.com/mwarkentin/django-watchman
Author: Michael Warkentin
Author-email: mwarkentin@gmail.com
License: BSD
Keywords: django-watchman
Platform: UNKNOWN
Classifier: Development Status :: 2 - Pre-Alpha
Classifier: Framework :: Django
Classifier: Intended Audience :: Developers
Classifier: License :: OSI Approved :: BSD License
Classifier: Natural Language :: English
Classifier: Programming Language :: Python :: 3
Classifier: Programming Language :: Python :: 3.5
Classifier: Programming Language :: Python :: 3.6
Classifier: Programming Language :: Python :: 3.7
Classifier: Programming Language :: Python :: 3.8
